[{"rank":4,"collection":"tiny dinos (eth)","volume":"57 ETH","percentChange":"+173%","floorPrice":"0.14 ETH","sales":354,"date":"2023-12-10 23:26:54"},{"rank":8,"collection":"Sugartown Oras by Zynga","volume":"110 ETH","percentChange":"-17%","floorPrice":"0.54 ETH","sales":256,"date":"2023-12-10 23:26:54"},{"rank":12,"collection":"Lumiterra Genesis Mystery Box","volume":"94 ETH","percentChange":"+357%","floorPrice":"0.28 ETH","sales":222,"date":"2023-12-10 23:26:54"},{"rank":14,"collection":"Echo of Intensity by Per Kristian Stoveland","volume":"8 ETH","percentChange":"+611%","floorPrice":"0.04 ETH","sales":210,"date":"2023-12-10 23:26:54"},{"rank":16,"collection":"y00ts","volume":"108 ETH","percentChange":"+79%","floorPrice":"0.59 ETH","sales":178,"date":"2023-12-10 23:26:54"},{"rank":17,"collection":"Redacted Remilio Babies","volume":"102 ETH","percentChange":"+2%","floorPrice":"0.62 ETH","sales":174,"date":"2023-12-10 23:26:54"},{"rank":15,"collection":"DeGods","volume":"613 ETH","percentChange":"-34%","floorPrice":"3.20 ETH","sales":194,"date":"2023-12-10 23:26:54"},{"rank":13,"collection":"Wanderers - RAM Beta Bundle","volume":"19 ETH","percentChange":"+67%","floorPrice":"0.11 ETH","sales":214,"date":"2023-12-10 23:26:54"},{"rank":10,"collection":"THE WHITE RABBIT","volume":"17 ETH","percentChange":"+90%","floorPrice":"0.02 ETH","sales":232,"date":"2023-12-10 23:26:54"},{"rank":11,"collection":"Trademark by Jack Butcher","volume":"49 ETH","percentChange":"+53%","floorPrice":"0.19 ETH","sales":229,"date":"2023-12-10 23:26:54"},{"rank":9,"collection":"Pudgy Penguins","volume":"2,778 ETH","percentChange":"+305%","floorPrice":"12.10 ETH","sales":238,"date":"2023-12-10 23:26:54"},{"rank":6,"collection":"Pixelmon Trainers - Generation 1","volume":"153 ETH","percentChange":"+1,101%","floorPrice":"0.54 ETH","sales":324,"date":"2023-12-10 23:26:54"},{"rank":7,"collection":"RAW DAWGS NFT","volume":"16 ETH","percentChange":"+83%","floorPrice":"0.05 ETH","sales":324,"date":"2023-12-10 23:26:54"},{"rank":5,"collection":"Pixelmon - Generation 1","volume":"698 ETH","percentChange":"+363%","floorPrice":"2.05 ETH","sales":325,"date":"2023-12-10 23:26:54"},{"rank":2,"collection":"Lil Pudgys","volume":"1,064 ETH","percentChange":"+211%","floorPrice":"1.17 ETH","sales":994,"date":"2023-12-10 23:26:54"},{"rank":3,"collection":"Pudgy Rods","volume":"267 ETH","percentChange":"+1,069%","floorPrice":"0.71 ETH","sales":364,"date":"2023-12-10 23:26:54"},{"rank":1,"collection":"BONIGO","volume":"149 ETH","percentChange":"+198%","floorPrice":"0.05 ETH","sales":3010,"date":"2023-12-10 23:26:54"},{"rank":24,"collection":"KILLABITS","volume":"24 ETH","percentChange":"+1,230%","floorPrice":"0.20 ETH","sales":128,"date":"2023-12-10 23:26:54"},{"rank":32,"collection":"Shrapnel Operators Collection","volume":"32 ETH","percentChange":"-24%","floorPrice":"0.32 ETH","sales":99,"date":"2023-12-10 23:26:54"},{"rank":36,"collection":"Senseless Stoics","volume":"15 ETH","percentChange":"+174%","floorPrice":"0.14 ETH","sales":86,"date":"2023-12-10 23:26:54"},{"rank":38,"collection":"Sofa Vision","volume":"8 ETH","percentChange":"+55%","floorPrice":"0.09 ETH","sales":85,"date":"2023-12-10 23:26:54"},{"rank":40,"collection":"KILLABEARS","volume":"88 ETH","percentChange":"+463%","floorPrice":"1.09 ETH","sales":81,"date":"2023-12-10 23:26:54"},{"rank":41,"collection":"Classic Pepes","volume":"11 ETH","percentChange":"+177%","floorPrice":"0.30 ETH","sales":77,"date":"2023-12-10 23:26:54"},{"rank":42,"collection":"MetaTrustDAO","volume":"5 ETH","percentChange":"-80%","floorPrice":"0.05 ETH","sales":77,"date":"2023-12-10 23:26:54"},{"rank":39,"collection":"Gh0stly Gh0sts","volume":"17 ETH","percentChange":"-79%","floorPrice":"0.20 ETH","sales":82,"date":"2023-12-10 23:26:54"},{"rank":37,"collection":"ChronoForge","volume":"24 ETH","percentChange":"-57%","floorPrice":"0.29 ETH","sales":85,"date":"2023-12-10 23:26:54"},{"rank":34,"collection":"Otherdeed Expanded","volume":"34 ETH","percentChange":"+73%","floorPrice":"0.30 ETH","sales":98,"date":"2023-12-10 23:26:54"},{"rank":35,"collection":"Opepen Edition","volume":"47 ETH","percentChange":"+0.06%","floorPrice":"0.44 ETH","sales":93,"date":"2023-12-10 23:26:54"},{"rank":33,"collection":"Kanpai Pandas","volume":"232 ETH","percentChange":"-17%","floorPrice":"2.45 ETH","sales":98,"date":"2023-12-10 23:26:54"},{"rank":28,"collection":"BlockGames Dice","volume":"60 ETH","percentChange":"-69%","floorPrice":"0.54 ETH","sales":113,"date":"2023-12-10 23:26:54"},{"rank":30,"collection":"Azuki Elementals","volume":"66 ETH","percentChange":"-36%","floorPrice":"0.64 ETH","sales":104,"date":"2023-12-10 23:26:54"},{"rank":31,"collection":"Parallel Alpha","volume":"7 ETH","percentChange":"+8%","floorPrice":"0.07 PRIME","sales":102,"date":"2023-12-10 23:26:54"},{"rank":29,"collection":"Quaere Genesis Pass","volume":"32 ETH","percentChange":"+325%","floorPrice":"0.33 ETH","sales":105,"date":"2023-12-10 23:26:54"},{"rank":26,"collection":"Binary: DEX","volume":"9 ETH","percentChange":"+113%","floorPrice":"0.06 ETH","sales":125,"date":"2023-12-10 23:26:54"},{"rank":27,"collection":"Mutant Ape Yacht Club","volume":"652 ETH","percentChange":"-35%","floorPrice":"5.59 ETH","sales":118,"date":"2023-12-10 23:26:54"},{"rank":25,"collection":"ANOMALY A.I. by Star Im","volume":"6 ETH","percentChange":"+38%","floorPrice":"0.03 ETH","sales":126,"date":"2023-12-10 23:26:54"},{"rank":20,"collection":"0N1 Force","volume":"32 ETH","percentChange":"+95%","floorPrice":"1.02 ETH","sales":143,"date":"2023-12-10 23:26:54"},{"rank":22,"collection":"Skyborne - Genesis Immortals","volume":"6 ETH","percentChange":"-83%","floorPrice":"0.05 ETH","sales":142,"date":"2023-12-10 23:26:54"},{"rank":23,"collection":"ChronoForge Support Airships","volume":"29 ETH","percentChange":"+0.23%","floorPrice":"0.20 ETH","sales":128,"date":"2023-12-10 23:26:54"},{"rank":21,"collection":"Sprotoladys","volume":"8 ETH","percentChange":"+23%","floorPrice":"0.05 ETH","sales":142,"date":"2023-12-10 23:26:54"},{"rank":18,"collection":"ParaX Medal","volume":"26 ETH","percentChange":"+24,973%","floorPrice":"0.20 ETH","sales":152,"date":"2023-12-10 23:26:54"},{"rank":19,"collection":"Rug Radio - Genesis NFT","volume":"34 ETH","percentChange":"+160%","floorPrice":"0.20 ETH","sales":147,"date":"2023-12-10 23:26:54"},{"rank":48,"collection":"Delabs Adventure Pass Official","volume":"15 ETH","percentChange":"+138%","floorPrice":"0.24 ETH","sales":67,"date":"2023-12-10 23:26:54"},{"rank":56,"collection":"Milady Maker","volume":"142 ETH","percentChange":"-38%","floorPrice":"3.20 ETH","sales":44,"date":"2023-12-10 23:26:54"},{"rank":60,"collection":"Skyborne - Nexian Gems","volume":"12 ETH","percentChange":"-83%","floorPrice":"0.28 ETH","sales":41,"date":"2023-12-10 23:26:54"},{"rank":62,"collection":"Terraforms by Mathcastles","volume":"56 ETH","percentChange":"+5%","floorPrice":"1.50 ETH","sales":38,"date":"2023-12-10 23:26:54"},{"rank":64,"collection":"Genuine Undead","volume":"5 ETH","percentChange":"+32%","floorPrice":"0.08 ETH","sales":38,"date":"2023-12-10 23:26:54"},{"rank":66,"collection":"Moonbirds","volume":"71 ETH","percentChange":"-68%","floorPrice":"2 ETH","sales":36,"date":"2023-12-10 23:26:54"},{"rank":67,"collection":"Treeverse Plots","volume":"25 ETH","percentChange":"-31%","floorPrice":"0.73 ETH","sales":36,"date":"2023-12-10 23:26:54"},{"rank":65,"collection":"My Curio Cards","volume":"9 ETH","percentChange":"+244%","floorPrice":"0.16 ETH","sales":37,"date":"2023-12-10 23:26:54"},{"rank":63,"collection":"The Memes by 6529","volume":"9 ETH","percentChange":"-43%","floorPrice":"0.03 ETH","sales":38,"date":"2023-12-10 23:26:54"},{"rank":61,"collection":"Doodles Original Collection","volume":"82 ETH","percentChange":"-20%","floorPrice":"2.19 ETH","sales":39,"date":"2023-12-10 23:26:54"},{"rank":58,"collection":"FLUF World: Burrows","volume":"23 ETH","percentChange":"+113%","floorPrice":"0.23 ETH","sales":44,"date":"2023-12-10 23:26:54"},{"rank":59,"collection":"The Sandbox","volume":"13 ETH","percentChange":"+69%","floorPrice":"0.28 ETH","sales":43,"date":"2023-12-10 23:26:54"},{"rank":57,"collection":"Creepz by OVERLORD","volume":"115 ETH","percentChange":"+4%","floorPrice":"2.75 ETH","sales":44,"date":"2023-12-10 23:26:54"},{"rank":52,"collection":"The Plague NFT","volume":"26 ETH","percentChange":"+579%","floorPrice":"0.45 ETH","sales":63,"date":"2023-12-10 23:26:54"},{"rank":54,"collection":"Nakamigos","volume":"11 ETH","percentChange":"-24%","floorPrice":"0.18 ETH","sales":57,"date":"2023-12-10 23:26:54"},{"rank":55,"collection":"Wonders of The First: Character Proofs","volume":"8 ETH","percentChange":"+71%","floorPrice":"0.10 ETH","sales":57,"date":"2023-12-10 23:26:54"},{"rank":53,"collection":"Opepunk by Doy","volume":"11 ETH","percentChange":"-48%","floorPrice":"0.13 ETH","sales":62,"date":"2023-12-10 23:26:54"},{"rank":50,"collection":"Pirate Nation - Founder\u0027s Pirates","volume":"22 ETH","percentChange":"+3%","floorPrice":"0.34 ETH","sales":64,"date":"2023-12-10 23:26:54"},{"rank":51,"collection":"Mintify Genesis","volume":"7 ETH","percentChange":"+123%","floorPrice":"0.09 ETH","sales":64,"date":"2023-12-10 23:26:54"},{"rank":49,"collection":"Balthazar raW Pass","volume":"19 ETH","percentChange":"-19%","floorPrice":"0.30 ETH","sales":65,"date":"2023-12-10 23:26:54"},{"rank":44,"collection":"Yogapetz","volume":"44 ETH","percentChange":"-50%","floorPrice":"0.61 ETH","sales":72,"date":"2023-12-10 23:26:54"},{"rank":46,"collection":"BEANZ Official","volume":"30 ETH","percentChange":"+20%","floorPrice":"0.45 ETH","sales":69,"date":"2023-12-10 23:26:54"},{"rank":47,"collection":"Worldwide Webb Land","volume":"14 ETH","percentChange":"+558%","floorPrice":"0.23 ETH","sales":68,"date":"2023-12-10 23:26:54"},{"rank":45,"collection":"CLONE X - X TAKASHI MURAKAMI","volume":"107 ETH","percentChange":"-14%","floorPrice":"1.53 ETH","sales":70,"date":"2023-12-10 23:26:54"},{"rank":43,"collection":"Azuki","volume":"457 ETH","percentChange":"-44%","floorPrice":"6.95 ETH","sales":73,"date":"2023-12-10 23:26:54"},{"rank":72,"collection":"Mocaverse","volume":"86 ETH","percentChange":"+231%","floorPrice":"2.90 ETH","sales":32,"date":"2023-12-10 23:26:54"},{"rank":80,"collection":"Impostors Genesis Aliens","volume":"15 ETH","percentChange":"+193%","floorPrice":"0.55 ETH","sales":26,"date":"2023-12-10 23:26:54"},{"rank":84,"collection":"Checks - VV Edition","volume":"18 ETH","percentChange":"-40%","floorPrice":"0.82 ETH","sales":23,"date":"2023-12-10 23:26:54"},{"rank":88,"collection":"Meebits","volume":"25 ETH","percentChange":"-22%","floorPrice":"1.31 ETH","sales":19,"date":"2023-12-10 23:26:54"},{"rank":90,"collection":"PartyBear","volume":"5 ETH","percentChange":"+115%","floorPrice":"0.27 ETH","sales":19,"date":"2023-12-10 23:26:54"},{"rank":91,"collection":"Bored Ape Kennel Club","volume":"30 ETH","percentChange":"-58%","floorPrice":"1.70 ETH","sales":18,"date":"2023-12-10 23:26:54"},{"rank":92,"collection":"Sappy Seals","volume":"13 ETH","percentChange":"-45%","floorPrice":"0.73 ETH","sales":18,"date":"2023-12-10 23:26:54"},{"rank":89,"collection":"My Pet Hooligan","volume":"20 ETH","percentChange":"+1%","floorPrice":"1.00 ETH","sales":19,"date":"2023-12-10 23:26:54"},{"rank":86,"collection":"L3E7 Worlds","volume":"110 ETH","percentChange":"+112%","floorPrice":"6.60 ETH","sales":21,"date":"2023-12-10 23:26:54"},{"rank":87,"collection":"Ultiverse - Electric Sheep","volume":"19 ETH","percentChange":"-39%","floorPrice":"1.18 ETH","sales":20,"date":"2023-12-10 23:26:54"},{"rank":85,"collection":"Mittaria Genesis","volume":"10 ETH","percentChange":"+30%","floorPrice":"0.44 ETH","sales":22,"date":"2023-12-10 23:26:54"},{"rank":82,"collection":"Pixels - Farm Land","volume":"34 ETH","percentChange":"+33%","floorPrice":"1.20 ETH","sales":25,"date":"2023-12-10 23:26:54"},{"rank":83,"collection":"Rare Pepe (2016 - 2018)","volume":"8 ETH","percentChange":"+1%","floorPrice":"0.02 ETH","sales":25,"date":"2023-12-10 23:26:54"},{"rank":81,"collection":"MetaHero: United Planets","volume":"6 ETH","percentChange":"-68%","floorPrice":"0.04 ETH","sales":26,"date":"2023-12-10 23:26:54"},{"rank":76,"collection":"goblintown.wtf","volume":"6 ETH","percentChange":"+367%","floorPrice":"0.22 ETH","sales":29,"date":"2023-12-10 23:26:54"},{"rank":78,"collection":"Otherside Vessels","volume":"6 ETH","percentChange":"-43%","floorPrice":"0.18 ETH","sales":28,"date":"2023-12-10 23:26:54"},{"rank":79,"collection":"Cool Cats","volume":"38 ETH","percentChange":"+6%","floorPrice":"1.06 ETH","sales":26,"date":"2023-12-10 23:26:54"},{"rank":77,"collection":"Flightless Space Agency","volume":"6 ETH","percentChange":"+1,282%","floorPrice":"0.22 ETH","sales":28,"date":"2023-12-10 23:26:54"},{"rank":74,"collection":"RTFKT Animus Egg 🥚","volume":"8 ETH","percentChange":"+128%","floorPrice":"0.30 ETH","sales":30,"date":"2023-12-10 23:26:54"},{"rank":75,"collection":"ENS: Ethereum Name Service","volume":"5 ETH","percentChange":"+10%","floorPrice":"\u003c 0.01 ETH","sales":30,"date":"2023-12-10 23:26:54"},{"rank":73,"collection":"Edenhorde","volume":"10 ETH","percentChange":"—","floorPrice":"0.15 ETH","sales":30,"date":"2023-12-10 23:26:54"},{"rank":68,"collection":"Moonbirds: Mythics","volume":"5 ETH","percentChange":"-14%","floorPrice":"0.15 ETH","sales":36,"date":"2023-12-10 23:26:54"},{"rank":70,"collection":"Bit Bears by Berachain","volume":"69 ETH","percentChange":"+357%","floorPrice":"2.77 ETH","sales":33,"date":"2023-12-10 23:26:54"},{"rank":71,"collection":"Bored Ape Yacht Club","volume":"935 ETH","percentChange":"-16%","floorPrice":"30.44 ETH","sales":32,"date":"2023-12-10 23:26:54"},{"rank":69,"collection":"Otherdeed for Otherside","volume":"55 ETH","percentChange":"+54%","floorPrice":"0.59 ETH","sales":34,"date":"2023-12-10 23:26:54"},{"rank":96,"collection":"Invisible Friends","volume":"6 ETH","percentChange":"+197%","floorPrice":"0.39 ETH","sales":16,"date":"2023-12-10 23:26:54"},{"rank":98,"collection":"Pixelmon Evolution 2 Serum","volume":"31 ETH","percentChange":"+129%","floorPrice":"2.30 ETH","sales":15,"date":"2023-12-10 23:26:54"},{"rank":99,"collection":"Parallel Avatars","volume":"13 ETH","percentChange":"-30%","floorPrice":"0.89 ETH","sales":15,"date":"2023-12-10 23:26:54"},{"rank":100,"collection":"Murakami.Flowers Official","volume":"6 ETH","percentChange":"-0.19%","floorPrice":"0.39 ETH","sales":15,"date":"2023-12-10 23:26:54"},{"rank":97,"collection":"RTFKT SKIN VIAL: EVO X","volume":"6 ETH","percentChange":"+953%","floorPrice":"0.03 ETH","sales":16,"date":"2023-12-10 23:26:54"},{"rank":94,"collection":"Women Unite - 10k Assemble","volume":"7 ETH","percentChange":"+58%","floorPrice":"0.32 ETH","sales":17,"date":"2023-12-10 23:26:54"},{"rank":95,"collection":"MetaHero: Generative Identities","volume":"6 ETH","percentChange":"+97%","floorPrice":"0.40 ETH","sales":16,"date":"2023-12-10 23:26:54"},{"rank":93,"collection":"Mavia Land","volume":"10 ETH","percentChange":"+231%","floorPrice":"0.54 ETH","sales":17,"date":"2023-12-10 23:26:54"}]